LICENSE
README.md
setup.cfg
setup.py
PillowScreenX/__init__.py
PillowScreenX/pillowscreenx.py
PillowScreenX.egg-info/PKG-INFO
PillowScreenX.egg-info/SOURCES.txt
PillowScreenX.egg-info/dependency_links.txt
PillowScreenX.egg-info/top_level.txt
PillowScreenX.egg-info/zip-safe