Metadata-Version: 2.1
Name: PillowScreenX
Version: 0.0.7
Summary: PillowScreenX is a powerful screenshot capturing tool that leverages the power of the Pillow library to provide high-quality screenshot captures.
Home-page: https://github.com/4akhilkumar/pillowscreenx
Author: Sai Akhil Kumar Reddy N
Author-email: 4akhilkumar@gmail.com
License: HPND
Keywords: Python,PillowScreenX,Screenshots,Path
Classifier: Development Status :: 4 - Beta
Classifier: Intended Audience :: Developers
Classifier: License :: OSI Approved :: Historical Permission Notice and Disclaimer (HPND)
Classifier: Programming Language :: Python :: 3
Classifier: Programming Language :: Python :: 3.7
Classifier: Programming Language :: Python :: 3.8
Classifier: Programming Language :: Python :: 3.9
Classifier: Programming Language :: Python :: 3.10
Classifier: Programming Language :: Python :: 3.11
License-File: LICENSE
